slappt/__init__.py
slappt/docker.py
slappt/exceptions.py
slappt/models.py
slappt/scripts.py
slappt/slappt.py
slappt/slurm.py
slappt/ssh.py
slappt/utils.py
slappt/tests/__init__.py
slappt/tests/test_cli.py
slappt/tests/test_docker.py
slappt/tests/test_scripts.py
slappt/tests/test_slappt.py
slappt/tests/test_ssh.py
slappt/tests/test_sshlurm.py
slappt-0.0.3.dist-info/METADATA
slappt-0.0.3.dist-info/WHEEL
slappt-0.0.3.dist-info/entry_points.txt
slappt-0.0.3.dist-info/top_level.txt
slappt-0.0.3.dist-info/RECORD
