Metadata-Version: 2.1
Name: slappt
Version: 0.0.3
Summary: generate slurm scripts for apptainer jobs
Home-page: https://github.com/Computational-Plant-Science/slappt
Download-URL: https://pypi.org/project/slappt
Author: Computational Plant Science Lab
Author-email: wbonelli@uga.edu
Maintainer: Wes Bonelli
Maintainer-email: wbonelli@uga.edu
License: BSD-3-Clause
Project-URL: Documentation, https://slappt.readthedocs.io
Project-URL: Bug Tracker, https://github.com/Computational-Plant-Science/slappt/issues
Project-URL: Source Code, https://github.com/Computational-Plant-Science/slappt
Keywords: hpc,containers,slurm,apptainer
Classifier: Development Status :: 3 - Alpha
Classifier: Intended Audience :: Science/Research
Classifier: License :: CC0 1.0 Universal (CC0 1.0) Public Domain Dedication
Classifier: Operating System :: Microsoft :: Windows
Classifier: Operating System :: POSIX
Classifier: Operating System :: Unix
Classifier: Operating System :: MacOS
Classifier: Programming Language :: Python
Classifier: Programming Language :: Python :: 3
Classifier: Programming Language :: Python :: 3.8
Classifier: Programming Language :: Python :: 3.9
Classifier: Programming Language :: Python :: 3.10
Classifier: Programming Language :: Python :: 3.11
Classifier: Programming Language :: Python :: 3 :: Only
Classifier: Topic :: System :: Distributed Computing
Classifier: Topic :: Scientific/Engineering :: Bio-Informatics
Requires-Python: >=3.8
Requires-Dist: click
Requires-Dist: httpx
Requires-Dist: filelock
Requires-Dist: paramiko
Requires-Dist: pyaml
Requires-Dist: requests
Requires-Dist: tenacity
Requires-Dist: tqdm
Provides-Extra: azure
Requires-Dist: azure-identity ; extra == 'azure'
Requires-Dist: azure-storage-blob ; extra == 'azure'
Provides-Extra: docs
Requires-Dist: sphinx ; extra == 'docs'
Requires-Dist: furo ; extra == 'docs'
Requires-Dist: myst-parser ; extra == 'docs'
Provides-Extra: gcs
Requires-Dist: google-cloud-storage ; extra == 'gcs'
Provides-Extra: irods
Requires-Dist: python-irodsclient ; extra == 'irods'
Provides-Extra: lint
Requires-Dist: black ; extra == 'lint'
Requires-Dist: flake8 ; extra == 'lint'
Requires-Dist: isort ; extra == 'lint'
Requires-Dist: pylint ; extra == 'lint'
Provides-Extra: s3
Requires-Dist: boto3 ; extra == 's3'
Requires-Dist: s3fs ; extra == 's3'
Provides-Extra: test
Requires-Dist: black ; extra == 'test'
Requires-Dist: flake8 ; extra == 'test'
Requires-Dist: isort ; extra == 'test'
Requires-Dist: pylint ; extra == 'test'
Requires-Dist: coverage ; extra == 'test'
Requires-Dist: coveralls ; extra == 'test'
Requires-Dist: jupyter ; extra == 'test'
Requires-Dist: jupytext ; extra == 'test'
Requires-Dist: pytest ; extra == 'test'
Requires-Dist: pytest-asyncio ; extra == 'test'
Requires-Dist: pytest-dotenv ; extra == 'test'
Requires-Dist: pytest-xdist ; extra == 'test'
